pupil_detectors/detector_base.cp311-win_amd64.pyd
pupil_detectors/roi.py
pupil_detectors/__init__.py
pupil_detectors/detector_2d/detector_2d.cp311-win_amd64.pyd
pupil_detectors/detector_2d/__init__.py
pupil_detectors-2.0.2.dist-info/DELVEWHEEL
pupil_detectors-2.0.2.dist-info/METADATA
pupil_detectors-2.0.2.dist-info/RECORD
pupil_detectors-2.0.2.dist-info/top_level.txt
pupil_detectors-2.0.2.dist-info/WHEEL
pupil_detectors.libs/.load-order-pupil_detectors-2.0.2
pupil_detectors.libs/concrt140.dll
pupil_detectors.libs/msvcp140.dll
pupil_detectors.libs/opencv_world460-012b3b79f380a5d813b78d836bf9f378.dll
