Metadata-Version: 2.1
Name: pupil-detectors
Version: 2.0.2
Summary: Pupil Labs 2D Pupil Detector
Home-page: https://github.com/pupil-labs/pupil-detectors
Author: Pupil Labs GmbH
Author-email: info@pupil-labs.com
License: MIT
Project-URL: Changelog, https://github.com/pupil-labs/pupil-detectors/blob/master/CHANGES.rst
Platform: UNKNOWN
Classifier: Development Status :: 5 - Production/Stable
Classifier: Intended Audience :: Developers
Classifier: License :: OSI Approved :: MIT License
Classifier: Programming Language :: Python :: 3
Classifier: Programming Language :: Python :: 3 :: Only
Requires-Python: >=3.6
Requires-Dist: numpy
Requires-Dist: opencv-python
Requires-Dist: cysignals ; platform_system != "Windows"
Requires-Dist: importlib-metadata ; python_version < "3.8"
Provides-Extra: docs
Requires-Dist: jaraco.packaging (>=9) ; extra == 'docs'
Requires-Dist: rst.linker (>=1.9) ; extra == 'docs'
Requires-Dist: sphinx ; extra == 'docs'
Provides-Extra: testing
Requires-Dist: pytest (>=6) ; extra == 'testing'
Requires-Dist: pytest-checkdocs (>=2.4) ; extra == 'testing'
Requires-Dist: pytest-cov ; extra == 'testing'
Requires-Dist: pytest-enabler (>=1.3) ; extra == 'testing'
Requires-Dist: pytest-mypy (>=0.9.1) ; (platform_python_implementation != "PyPy") and extra == 'testing'
